{
    "/dist/js/customizer.js": "/dist/js/customizer.js?id=246a16898a63b06a0633",
    "/dist/js/customizer.js.map": "/dist/js/customizer.js.map?id=f18e14d1ce0ebf68c39e",
    "/dist/js/editor.js": "/dist/js/editor.js?id=3519f6c3b6ffc89ff052",
    "/dist/js/editor.js.map": "/dist/js/editor.js.map?id=1bfef8744ed55490a08c",
    "/dist/js/manifest.js": "/dist/js/manifest.js?id=35fefc822368cea88338",
    "/dist/js/manifest.js.map": "/dist/js/manifest.js.map?id=82a2b9fd707e835b1bb5",
    "/dist/js/vendor.js": "/dist/js/vendor.js?id=4dbddd7ef3ce7947bc82",
    "/dist/js/vendor.js.map": "/dist/js/vendor.js.map?id=263eb0da539b880867b2",
    "/js/app.js": "/js/app.js?id=3b94e6b27e2656dc3205",
    "/css/style.css": "/css/style.css?id=31c3a0df3999b724f913",
    "/js/app.js.map": "/js/app.js.map?id=bb6e91694bdc77cde795",
    "/css/style.css.map": "/css/style.css.map?id=dfc29bb198f8bb4f33ca"
}
